simaticai/README.md
simaticai/__main__.py
simaticai/data/__init__.py
simaticai/data/log_module-1.0.1-py3-none-any.whl
simaticai/data/schemas/__init__.py
simaticai/data/schemas/datalink.schema.json
simaticai/data/schemas/pipeline.schema.json
simaticai/data/schemas/runtime.schema.json
simaticai/deploy/__init__.py
simaticai/deploy/component.py
simaticai/deploy/gpuruntime_component.py
simaticai/deploy/pipeline.py
simaticai/deploy/pipeline_data.py
simaticai/deploy/pipeline_page.py
simaticai/deploy/python_component.py
simaticai/deployment.py
simaticai/helpers/__init__.py
simaticai/helpers/model_config.py
simaticai/helpers/pep508.py
simaticai/helpers/reporter.py
simaticai/helpers/tempfiles.py
simaticai/helpers/yaml_helper.py
simaticai/model_config_pb2.py
simaticai/packaging/__init__.py
simaticai/packaging/constants.py
simaticai/packaging/python_dependencies.py
simaticai/packaging/wheelhouse.py
simaticai/testing/__init__.py
simaticai/testing/component_runner.py
simaticai/testing/data_stream.py
simaticai/testing/docker_venv.py
simaticai/testing/gpuruntime_requirements.txt
simaticai/testing/pipeline_runner.py
simaticai/testing/pipeline_validator.py
simaticai/testing/run_component.py
simaticai/testing/run_gpuruntime_component.py
simaticai/testing/runner_config.py
simaticai/testing/timeseries_stream.py
simaticai/testing/vca_stream.py
simaticai-2.5.0.dist-info/METADATA
simaticai-2.5.0.dist-info/WHEEL
simaticai-2.5.0.dist-info/entry_points.txt
simaticai-2.5.0.dist-info/RECORD
