Metadata-Version: 2.3
Name: simaticai
Version: 2.5.0
Summary: AI Software Development Kit
License: MIT
Author: Siemens AG
Requires-Python: >=3.10.0
Classifier: License :: OSI Approved :: MIT License
Classifier: Operating System :: OS Independent
Classifier: Programming Language :: Python :: 3
Classifier: Programming Language :: Python :: 3.10
Classifier: Programming Language :: Python :: 3.11
Classifier: Programming Language :: Python :: 3.12
Classifier: Programming Language :: Python :: 3.13
Requires-Dist: MarkupPy (>=1.14,<2.0)
Requires-Dist: Parsley (==1.3)
Requires-Dist: PyYAML (>=6.0.1,<7.0.0)
Requires-Dist: idna (>=3.7)
Requires-Dist: joblib (>=1.2.0)
Requires-Dist: jsonschema (>=4.0.1,<5.0.0)
Requires-Dist: onnx (>=1.17,<2.0)
Requires-Dist: onnxruntime (>=1.17,<2.0)
Requires-Dist: opencv-python-headless (>=4.9.0.80)
Requires-Dist: pip (>23.2.1)
Requires-Dist: protobuf (>=5.29.4,<6.0.0)
Requires-Dist: requests (>=2.32.3)
Requires-Dist: tomli (>=2.2.1)
Requires-Dist: wheel (>=0.43.0)
Project-URL: Changelog, https://github.com/industrial-edge/ai-sdk/blob/main/CHANGELOG.md
Project-URL: Documentation, https://github.com/industrial-edge/ai-sdk-tutorials
Project-URL: Homepage, https://github.com/industrial-edge/ai-sdk
Project-URL: Issues, https://github.com/industrial-edge/ai-sdk/issues
Project-URL: Repository, https://github.com/industrial-edge/ai-sdk.git
